immuna_prices/__init__.py
immuna_prices/cmc.py
immuna_prices/cmc_currency_info_response.type.py
immuna_prices/cmc_trending_response_type.py
immuna_prices/db.py
immuna_prices/db_peewee.py
immuna_prices/utils.py
i_prices-1.0.0.dist-info/WHEEL
i_prices-1.0.0.dist-info/METADATA
i_prices-1.0.0.dist-info/RECORD
