Metadata-Version: 2.1
Name: i-prices
Version: 1.0.0
Summary: 
Author: Dima v
Author-email: dima@immuna.xyz
Requires-Python: >=3.10,<4.0
Classifier: Programming Language :: Python :: 3
Classifier: Programming Language :: Python :: 3.10
Classifier: Programming Language :: Python :: 3.11
Requires-Dist: cryptocmd (>=0.6.1,<0.7.0)
Requires-Dist: load-dotenv (>=0.1.0,<0.2.0)
Requires-Dist: pandas (>=1.5.1,<2.0.0)
Requires-Dist: peewee (>=3.15.3,<4.0.0)
Requires-Dist: prisma (>=0.7.0,<0.8.0)
Requires-Dist: psycopg2-binary (>=2.9.5,<3.0.0)
Requires-Dist: python-dateutil (>=2.8.2,<3.0.0)
Requires-Dist: requests (>=2.28.1,<3.0.0)
